ortex/__init__.py
ortex/api.py
ortex/client.py
ortex/exceptions.py
ortex/py.typed
ortex/response.py
ortex/throttler.py
ortex-1.0.4.dist-info/METADATA
ortex-1.0.4.dist-info/WHEEL
ortex-1.0.4.dist-info/licenses/LICENSE
ortex-1.0.4.dist-info/RECORD
